feast/__init__.py
feast/aggregation.py
feast/base_feature_view.py
feast/batch_feature_view.py
feast/cli.py
feast/constants.py
feast/data_format.py
feast/data_source.py
feast/driver_test_data.py
feast/entity.py
feast/errors.py
feast/feast_object.py
feast/feature.py
feast/feature_logging.py
feast/feature_server.py
feast/feature_service.py
feast/feature_store.py
feast/feature_view.py
feast/feature_view_projection.py
feast/field.py
feast/file_utils.py
feast/flags_helper.py
feast/importer.py
feast/inference.py
feast/names.py
feast/offline_server.py
feast/on_demand_feature_view.py
feast/online_response.py
feast/project_metadata.py
feast/proto_json.py
feast/py.typed
feast/registry_server.py
feast/repo_config.py
feast/repo_contents.py
feast/repo_operations.py
feast/saved_dataset.py
feast/stream_feature_view.py
feast/transformation_server.py
feast/type_map.py
feast/types.py
feast/ui_server.py
feast/utils.py
feast/value_type.py
feast/version.py
feast/wait.py
feast/diff/__init__.py
feast/diff/infra_diff.py
feast/diff/property_diff.py
feast/diff/registry_diff.py
feast/dqm/__init__.py
feast/dqm/errors.py
feast/dqm/profilers/__init__.py
feast/dqm/profilers/ge_profiler.py
feast/dqm/profilers/profiler.py
feast/embedded_go/__init__.py
feast/embedded_go/online_features_service.py
feast/embedded_go/type_map.py
feast/infra/__init__.py
feast/infra/infra_object.py
feast/infra/key_encoding_utils.py
feast/infra/passthrough_provider.py
feast/infra/provider.py
feast/infra/contrib/__init__.py
feast/infra/contrib/grpc_server.py
feast/infra/contrib/spark_kafka_processor.py
feast/infra/contrib/stream_processor.py
feast/infra/feature_servers/__init__.py
feast/infra/feature_servers/base_config.py
feast/infra/feature_servers/local_process/__init__.py
feast/infra/feature_servers/local_process/config.py
feast/infra/feature_servers/multicloud/Dockerfile
feast/infra/feature_servers/multicloud/Dockerfile.dev
feast/infra/feature_servers/multicloud/__init__.py
feast/infra/materialization/__init__.py
feast_gitlab-0.1.2.dist-info/LICENSE
feast_gitlab-0.1.2.dist-info/METADATA
feast_gitlab-0.1.2.dist-info/WHEEL
feast_gitlab-0.1.2.dist-info/entry_points.txt
feast_gitlab-0.1.2.dist-info/top_level.txt
feast_gitlab-0.1.2.dist-info/RECORD
